README.md
setup.cfg
setup.py
emailconnection.egg-info/PKG-INFO
emailconnection.egg-info/SOURCES.txt
emailconnection.egg-info/dependency_links.txt
emailconnection.egg-info/requires.txt
emailconnection.egg-info/top_level.txt
src/emailconnection/__init__.py
src/emailconnection/email_connection.py
src/emailconnection/email_queries.py