Metadata-Version: 1.1
Name: emailconnection
Version: 0.0.3
Summary: Email Connections and Queries Handler
Home-page: https://github.com/ByPrice/emailconnection
Author: Yogesh Yadav
Author-email: yogeshdtu@gmail.com
License: MIT
Download-URL: https://github.com/ByPrice/emailconnection
Keywords: email,emailconnection
Platform: cross-platfom
Platform: platform-independent
Classifier: Intended Audience :: Developers
Classifier: Topic :: Software Development :: Build Tools
Classifier: Programming Language :: Python :: 3.6
